[
    {
        "id": 1,
        "idCategoria": 1,
        "nombre":"Ghost Recon",
        "marca":"ubisoft",
        "modelo":"",
        "precio":4890,
        "stock":1,
        "img":"ghostReconPS4.jpg"
    },
    {
        "id": 2,
        "idCategoria": 2,
        "nombre":"Litle Nightmares 2",
        "marca":"Supermassive Games",
        "modelo":"",
        "precio":4890,
        "stock":4,
        "img":"littleNightmares2PS4.jpg"
    },
    {
        "id": 3,
        "idCategoria": 3,
        "nombre":"Play Station 4 1tb - Combo Mega",
        "marca":"sony",
        "modelo":"",
        "precio":4890,
        "stock":10,
        "img":"megaPackPS4.jpg"
    },
    {
        "id": 4,
        "idCategoria": 4,
        "nombre":"Nintendo Switch Neon Red y Blue",
        "marca":"Nintendo",
        "modelo":"",
        "precio":149000,
        "stock":2,
        "img":"nintendoSwitchRedyBlue.jpg"
    },
    {
        "id": 5,
        "idCategoria": 5,
        "nombre":"Resident Evil 2 remake",
        "marca":"capcom",
        "modelo":"",
        "precio":7999,
        "stock":2,
        "img":"residentEvil2RMKPS4.jpg"
    },
    {
        "id": 6,
        "idCategoria": 6,
        "nombre":"Resident Evil 8",
        "marca":"capcom",
        "modelo":"",
        "precio":12990,
        "stock":4,
        "img":"residentEvil8PS4.jpg"
    },
    {
        "id": 7,
        "idCategoria": 7,
        "nombre":"Consola Retro Game Family",
        "marca":"",
        "modelo":"",
        "precio":4890,
        "stock":20,
        "img":"retroGameFamily300en1.jpg"
    },
    {
        "id": 8,
        "idCategoria": 8,
        "nombre":"Consola Steam Deck 256GB",
        "marca":"steam",
        "modelo":"",
        "precio":359990,
        "stock":12,
        "img":"SteamDeck.jpg"
    },
    {
        "id": 9,
        "idCategoria": 9,
        "nombre":"The Last Of Us Part2",
        "marca":"ps4",
        "modelo":"",
        "precio":6599,
        "stock":4,
        "img":"theLastOfUsPS4.jpg"
    },
    {
        "id": 10,
        "idCategoria": 10,
        "nombre":"Xbox Series X 1TB",
        "marca":"XBOX",
        "modelo":"Series X",
        "precio":269990,
        "stock":10,
        "img":"XBOXseriesX.jpg"
    }


]